<?xml version="1.0" encoding="UTF-8"?>
<mapping>
    <in>
        <fields>
            <field>
                <from>ocp_product_sku</from>
                <to>ocp_product_sku</to>
            </field>
            <field>
                <from>ocp_color</from>
                <to>ocp_color</to>
            </field>              
            <field>
                <from>category_id</from>
                <to>category_id</to>
            </field>            
        </fields>
    </in>
</mapping>